{
	"sertificat": {
		"getSertBtn": ".btn--md[data-modal='sertificatModal']",
		"modal": ".modal[data-modal='sertificatModal']",
		"modalName": ".modal[data-modal='sertificatModal'] .input[data-placeholder='Имя']",
		"modalPhone": ".modal[data-modal='sertificatModal'] .input[data-placeholder='Телефон']",
		"modalBtn": ".modal[data-modal='sertificatModal'] .btn--md.btn--mark.btn--full"
	},
	"aktsii": {
		"getModal": ".sale-el:nth-child(1)"
	},
	"otzyvy": {
		"form": ".main-cont-sm .contract",
		"formBtn": ".main-cont-sm .contract .js-add-review",
		"name": ".main-cont-sm .contract .input[data-placeholder='Ваше имя']",
		"phone": ".main-cont-sm .contract .input[data-placeholder='Телефон']",
		"text": ".main-cont-sm .contract .input[data-placeholder='Ваш отзыв']",
		"select": ".main-cont-sm .contract .dropdown-current",
		"selectVal": ".main-cont-sm .contract .dropdown-menu__el[data-value='strong']",
		"modalTrue": ".modal[data-modal='success']",
		"modalTrueBtn": ".modal[data-modal='success'] .btn--md.btn--light.btn--full"
	},
	"faq": {
		"list": ".faq-type__el",
		"elQuestion": ".accordion.active .accordion__el:nth-child(1)",
		"form": ".main-cont-sm .contract",
		"name": ".main-cont-sm .contract .input[data-placeholder='Ваше имя']",
		"phone": ".main-cont-sm .contract .input[data-placeholder='Почта или Телефон']",
		"text": ".main-cont-sm .contract .input[data-placeholder='Комментарий']",
		"formBtn": ".main-cont-sm .contract .js-faq-form",
		"modalTrue": ".modal[data-modal='success']",
		"modalTrueBtn": ".modal[data-modal='success'] .btn--md.btn--light.btn--full"
	},
	"blog": {
		"list": ".tag-el",
		"form": ".subscribe-block",
		"mail": ".subscribe-block .input[data-placeholder='Email']",
		"formBtn": ".js-blog-subscribe",
		"modalTrue": ".modal[data-modal='success']",
		"modalTrueBtn": ".modal[data-modal='success'] .btn--md.btn--light.btn--full"
	}
}